alpax/__about__.py
alpax/__init__.py
alpax/py.typed
alpax-0.2.0.dist-info/METADATA
alpax-0.2.0.dist-info/WHEEL
alpax-0.2.0.dist-info/licenses/LICENSE.txt
alpax-0.2.0.dist-info/RECORD
