Metadata-Version: 2.3
Name: alpax
Version: 0.2.0
Summary: Generate custom Ableton Live packs
Project-URL: Documentation, https://github.com/kmontag/alpax#readme
Project-URL: Issues, https://github.com/kmontag/alpax/issues
Project-URL: Source, https://github.com/kmontag/alpax
Author-email: Kevin Montag <kmontag@cs.stanford.edu>
License-Expression: MIT
License-File: LICENSE.txt
Classifier: Development Status :: 3 - Alpha
Classifier: Programming Language :: Python
Classifier: Programming Language :: Python :: 3.9
Classifier: Programming Language :: Python :: 3.10
Classifier: Programming Language :: Python :: 3.11
Classifier: Programming Language :: Python :: 3.12
Classifier: Programming Language :: Python :: Implementation :: CPython
Classifier: Programming Language :: Python :: Implementation :: PyPy
Requires-Python: >=3.9
